traderhub_tradeanalytica/__init__.py
traderhub_tradeanalytica/backtest.py
traderhub_tradeanalytica/executors/__init__.py
traderhub_tradeanalytica/executors/checker_mixins.py
traderhub_tradeanalytica/executors/condition_checker.py
traderhub_tradeanalytica/executors/patternpy/__init__.py
traderhub_tradeanalytica/executors/patternpy/functions_map.py
traderhub_tradeanalytica/executors/patternpy/hard_data.py
traderhub_tradeanalytica/executors/patternpy/tradingpatterns.py
traderhub_tradeanalytica/mixins/__init__.py
traderhub_tradeanalytica/mixins/initialise.py
traderhub_tradeanalytica/mixins/metrics.py
traderhub_tradeanalytica/references/__init__.py
traderhub_tradeanalytica/references/cdl_pattern_models.py
traderhub_tradeanalytica/references/pattern_models.py
traderhub_tradeanalytica/references/price_models.py
traderhub_tradeanalytica/references/indicators_models/__init__.py
traderhub_tradeanalytica/references/indicators_models/constants.py
traderhub_tradeanalytica/references/indicators_models/cycles.py
traderhub_tradeanalytica/references/indicators_models/indicators_talib_map.py
traderhub_tradeanalytica/references/indicators_models/momentum.py
traderhub_tradeanalytica/references/indicators_models/overlap.py
traderhub_tradeanalytica/references/indicators_models/trend.py
traderhub_tradeanalytica/references/indicators_models/volatility.py
traderhub_tradeanalytica/references/indicators_models/volume.py
traderhub_tradeanalytica-0.1.6.dist-info/METADATA
traderhub_tradeanalytica-0.1.6.dist-info/WHEEL
traderhub_tradeanalytica-0.1.6.dist-info/top_level.txt
traderhub_tradeanalytica-0.1.6.dist-info/RECORD
