Metadata-Version: 2.1
Name: traderhub_tradeanalytica
Version: 0.1.6
Summary: TraderHub library for trade strategy analyse
Home-page: https://github.com/single-service/traderhub-tradeanalytica-lib
Author: DmitriySosedov
Author-email: d.i.sosedov@gmail.com
Project-URL: GitHub, https://github.com/single-service/traderhub-tradeanalytica-lib
Keywords: trade analytica backtesting traderhub
Classifier: Programming Language :: Python :: 3.10
Classifier: License :: OSI Approved :: MIT License
Classifier: Operating System :: OS Independent
Requires-Python: >=3.10
Requires-Dist: pandas>=2.2.2
Requires-Dist: TA-Lib-Precompiled>=0.4.25
Requires-Dist: numpy<1.26.0,>=1.24.2
Requires-Dist: pandas-ta>=0.3.14b
Requires-Dist: sortedcontainers>=2.4.0
